djmoney/__init__.py
djmoney/_compat.py
djmoney/admin.py
djmoney/apps.py
djmoney/money.py
djmoney/money.pyi
djmoney/py.typed
djmoney/serializers.py
djmoney/settings.py
djmoney/utils.py
djmoney/contrib/__init__.py
djmoney/contrib/django_rest_framework/__init__.py
djmoney/contrib/django_rest_framework/fields.py
djmoney/contrib/exchange/__init__.py
djmoney/contrib/exchange/admin.py
djmoney/contrib/exchange/exceptions.py
djmoney/contrib/exchange/models.py
djmoney/contrib/exchange/backends/__init__.py
djmoney/contrib/exchange/backends/base.py
djmoney/contrib/exchange/backends/fixer.py
djmoney/contrib/exchange/backends/openexchangerates.py
djmoney/contrib/exchange/management/__init__.py
djmoney/contrib/exchange/management/base.py
djmoney/contrib/exchange/management/commands/__init__.py
djmoney/contrib/exchange/management/commands/clear_rates.py
djmoney/contrib/exchange/management/commands/update_rates.py
djmoney/contrib/exchange/migrations/0001_initial.py
djmoney/contrib/exchange/migrations/__init__.py
djmoney/forms/__init__.py
djmoney/forms/fields.py
djmoney/forms/widgets.py
djmoney/models/__init__.py
djmoney/models/fields.py
djmoney/models/managers.py
djmoney/models/validators.py
djmoney/templatetags/__init__.py
djmoney/templatetags/djmoney.py
django_money-3.5.3.dist-info/LICENSE.txt
django_money-3.5.3.dist-info/METADATA
django_money-3.5.3.dist-info/WHEEL
django_money-3.5.3.dist-info/top_level.txt
django_money-3.5.3.dist-info/RECORD
