Metadata-Version: 2.1
Name: django-money
Version: 3.5.3
Summary: Adds support for using money and currency fields in django models and forms. Uses py-moneyed as the money implementation.
Home-page: https://github.com/django-money/django-money
Maintainer: Greg Reinbach
Maintainer-email: greg@reinbach.com
License: BSD
Keywords: django,py-money,money
Platform: Any
Classifier: Development Status :: 5 - Production/Stable
Classifier: Intended Audience :: Developers
Classifier: License :: OSI Approved :: BSD License
Classifier: Operating System :: OS Independent
Classifier: Framework :: Django
Classifier: Framework :: Django :: 4.2
Classifier: Framework :: Django :: 5.0
Classifier: Framework :: Django :: 5.1
Classifier: Programming Language :: Python
Classifier: Programming Language :: Python :: 3
Classifier: Programming Language :: Python :: 3.8
Classifier: Programming Language :: Python :: 3.9
Classifier: Programming Language :: Python :: 3.10
Classifier: Programming Language :: Python :: 3.11
Classifier: Programming Language :: Python :: 3.12
Classifier: Programming Language :: Python :: Implementation :: CPython
Classifier: Programming Language :: Python :: Implementation :: PyPy
Requires-Python: >=3.7
License-File: LICENSE.txt
Requires-Dist: setuptools
Requires-Dist: Django>=2.2
Requires-Dist: py-moneyed<3.1,>=2.0
Provides-Extra: test
Requires-Dist: pytest<8.3,>=8.2; extra == "test"
Requires-Dist: pytest-django; extra == "test"
Requires-Dist: pytest-cov; extra == "test"
Requires-Dist: mixer; extra == "test"
Requires-Dist: mypy; extra == "test"
Requires-Dist: django-stubs; extra == "test"
Provides-Extra: exchange
Requires-Dist: certifi; extra == "exchange"
